datagpt/__init__.py
datagpt/__init__.pyi
datagpt/chatgpt.py
datagpt/chatgpt.pyi
datagpt/packs/__init__.py
datagpt/packs/__init__.pyi
datagpt/packs/openai_.py
datagpt/packs/openai_.pyi
datagpt-0.2.0.dist-info/LICENSE
datagpt-0.2.0.dist-info/METADATA
datagpt-0.2.0.dist-info/WHEEL
datagpt-0.2.0.dist-info/RECORD
