Metadata-Version: 2.3
Name: datagpt
Version: 0.2.0
Summary: DataGPT for managing instructions and databases
License: MIT
Author: yayayru
Requires-Python: >=3.12,<4.0
Classifier: License :: OSI Approved :: MIT License
Classifier: Programming Language :: Python :: 3
Classifier: Programming Language :: Python :: 3.12
Classifier: Programming Language :: Python :: 3.13
Requires-Dist: openai (>=1.55.3,<2.0.0)
Requires-Dist: python-dotenv (>=1.0.1,<2.0.0)
